imaginary/__init__.py
imaginary_fabric-0.1.0.dist-info/METADATA
imaginary_fabric-0.1.0.dist-info/WHEEL
imaginary_fabric-0.1.0.dist-info/top_level.txt
imaginary_fabric-0.1.0.dist-info/RECORD
