Metadata-Version: 2.4
Name: imaginary-fabric
Version: 0.1.0
Summary: A minimal example Python package.
Author-email: Your Name <you@example.com>
Project-URL: Homepage, https://github.com/Imaginary-Biolabs/fabric
Project-URL: Repository, https://github.com/Imaginary-Biolabs/fabric
Project-URL: Issues, https://github.com/Imaginary-Biolabs/fabric/issues
Keywords: example,package
Classifier: Programming Language :: Python :: 3
Classifier: Operating System :: OS Independent
Requires-Python: >=3.9
